{
  "resourceType": "Patient",
  "id": "1a6768b2-a492-0e9f-984d-b268fe945c5b",
  "meta": {
    "profile": [
      "http://hl7.org/fhir/R4/patient.html"
    ],
    "versionId": "1",
    "lastUpdated": "2025-08-28T05:15:06.832526"
  },
  "identifier": [
    {
      "system": "http://tmu.edu.tw/fhir/alzheimers/patient-id",
      "value": "3e6aadee8e888d5d"
    }
  ],
  "active": true,
  "gender": "male",
  "extension": [
    {
      "url": "http://tmu.edu.tw/fhir/alzheimers/age-group",
      "valueString": "未知年齡"
    }
  ]
}