{
  "resourceType": "Patient",
  "id": "256a5bb8-9f0c-ea9a-ac54-1e57f16d7706",
  "meta": {
    "profile": [
      "http://hl7.org/fhir/R4/patient.html"
    ],
    "versionId": "1",
    "lastUpdated": "2025-08-28T05:15:41.012154"
  },
  "identifier": [
    {
      "system": "http://tmu.edu.tw/fhir/alzheimers/patient-id",
      "value": "62fac00ee02ddb45"
    }
  ],
  "active": true,
  "gender": "female",
  "extension": [
    {
      "url": "http://tmu.edu.tw/fhir/alzheimers/age-group",
      "valueString": "未知年齡"
    }
  ]
}