{
  "resourceType": "Patient",
  "id": "548ddaa9-f3d3-1dec-babe-11b0fe8815d4",
  "meta": {
    "profile": [
      "http://hl7.org/fhir/R4/patient.html"
    ],
    "versionId": "1",
    "lastUpdated": "2025-08-28T05:15:43.592603"
  },
  "identifier": [
    {
      "system": "http://tmu.edu.tw/fhir/alzheimers/patient-id",
      "value": "56cb1d449e50d447"
    }
  ],
  "active": true,
  "gender": "male",
  "extension": [
    {
      "url": "http://tmu.edu.tw/fhir/alzheimers/age-group",
      "valueString": "80-89歲"
    }
  ]
}