{
  "resourceType": "Patient",
  "id": "5ff7b107-fceb-4dbf-a577-e6e6337a1e3b",
  "meta": {
    "profile": [
      "http://hl7.org/fhir/R4/patient.html"
    ],
    "versionId": "1",
    "lastUpdated": "2025-08-28T05:14:39.625843"
  },
  "identifier": [
    {
      "system": "http://tmu.edu.tw/fhir/alzheimers/patient-id",
      "value": null
    }
  ],
  "active": true,
  "gender": "unknown",
  "extension": [
    {
      "url": "http://tmu.edu.tw/fhir/alzheimers/age-group",
      "valueString": "90+歲"
    }
  ]
}