{
  "resourceType": "Patient",
  "id": "964c7ca7-5b8e-0811-584c-be09d25ed836",
  "meta": {
    "profile": [
      "http://hl7.org/fhir/R4/patient.html"
    ],
    "versionId": "1",
    "lastUpdated": "2025-08-28T05:14:39.555252"
  },
  "identifier": [
    {
      "system": "http://tmu.edu.tw/fhir/alzheimers/patient-id",
      "value": "8dacb519c93ca054"
    }
  ],
  "active": true,
  "gender": "female",
  "extension": [
    {
      "url": "http://tmu.edu.tw/fhir/alzheimers/age-group",
      "valueString": "未知年齡"
    }
  ]
}