{
  "resourceType": "Patient",
  "id": "9bd22670-8898-4645-8cdd-4a7c7bc98773",
  "meta": {
    "profile": [
      "http://hl7.org/fhir/R4/patient.html"
    ],
    "versionId": "1",
    "lastUpdated": "2025-08-28T05:15:43.653258"
  },
  "identifier": [
    {
      "system": "http://tmu.edu.tw/fhir/alzheimers/patient-id",
      "value": null
    }
  ],
  "active": true,
  "gender": "unknown",
  "extension": [
    {
      "url": "http://tmu.edu.tw/fhir/alzheimers/age-group",
      "valueString": "90+歲"
    }
  ]
}