{
  "resourceType": "Patient",
  "id": "a3c18204-c107-2ee0-df26-251ea64922de",
  "meta": {
    "profile": [
      "http://hl7.org/fhir/R4/patient.html"
    ],
    "versionId": "1",
    "lastUpdated": "2025-08-28T05:15:41.083726"
  },
  "identifier": [
    {
      "system": "http://tmu.edu.tw/fhir/alzheimers/patient-id",
      "value": "b3a27f2b99a1fa02"
    }
  ],
  "active": true,
  "gender": "male",
  "extension": [
    {
      "url": "http://tmu.edu.tw/fhir/alzheimers/age-group",
      "valueString": "90+歲"
    }
  ]
}