{
  "resourceType": "Patient",
  "id": "b00fcb5c-5642-4e4e-8e9b-cc9e88a7173a",
  "meta": {
    "profile": [
      "http://hl7.org/fhir/R4/patient.html"
    ],
    "versionId": "1",
    "lastUpdated": "2025-08-28T05:14:39.633898"
  },
  "identifier": [
    {
      "system": "http://tmu.edu.tw/fhir/alzheimers/patient-id",
      "value": null
    }
  ],
  "active": true,
  "gender": "unknown",
  "extension": [
    {
      "url": "http://tmu.edu.tw/fhir/alzheimers/age-group",
      "valueString": "90+歲"
    }
  ]
}