{
  "resourceType": "Patient",
  "id": "b4e6a64b-2765-984a-aa55-de50aea85076",
  "meta": {
    "profile": [
      "http://hl7.org/fhir/R4/patient.html"
    ],
    "versionId": "1",
    "lastUpdated": "2025-08-28T05:15:06.876775"
  },
  "identifier": [
    {
      "system": "http://tmu.edu.tw/fhir/alzheimers/patient-id",
      "value": "abc395d55ab38d72"
    }
  ],
  "active": true,
  "gender": "female",
  "extension": [
    {
      "url": "http://tmu.edu.tw/fhir/alzheimers/age-group",
      "valueString": "90+歲"
    }
  ]
}