{
  "resourceType": "Patient",
  "id": "c6777e96-5db2-a75c-553c-d4c3aeb5499b",
  "meta": {
    "profile": [
      "http://hl7.org/fhir/R4/patient.html"
    ],
    "versionId": "1",
    "lastUpdated": "2025-08-28T05:15:06.843899"
  },
  "identifier": [
    {
      "system": "http://tmu.edu.tw/fhir/alzheimers/patient-id",
      "value": "9179cb0b1dc48559"
    }
  ],
  "active": true,
  "gender": "male",
  "extension": [
    {
      "url": "http://tmu.edu.tw/fhir/alzheimers/age-group",
      "valueString": "未知年齡"
    }
  ]
}