{
  "resourceType": "Patient",
  "id": "d019cc6c-f479-1be5-f320-2998eecd628f",
  "meta": {
    "profile": [
      "http://hl7.org/fhir/R4/patient.html"
    ],
    "versionId": "1",
    "lastUpdated": "2025-08-28T05:15:43.589129"
  },
  "identifier": [
    {
      "system": "http://tmu.edu.tw/fhir/alzheimers/patient-id",
      "value": "8ad373d2bad52542"
    }
  ],
  "active": true,
  "gender": "female",
  "extension": [
    {
      "url": "http://tmu.edu.tw/fhir/alzheimers/age-group",
      "valueString": "70-79歲"
    }
  ]
}