{
  "resourceType": "Patient",
  "id": "ee75dacb-2d96-cf16-1b05-2f0884d29409",
  "meta": {
    "profile": [
      "http://hl7.org/fhir/R4/patient.html"
    ],
    "versionId": "1",
    "lastUpdated": "2025-08-28T05:14:39.574228"
  },
  "identifier": [
    {
      "system": "http://tmu.edu.tw/fhir/alzheimers/patient-id",
      "value": "1464bc0eb58f7c0d"
    }
  ],
  "active": true,
  "gender": "male",
  "extension": [
    {
      "url": "http://tmu.edu.tw/fhir/alzheimers/age-group",
      "valueString": "未知年齡"
    }
  ]
}