{
  "resourceType": "Observation",
  "id": "0d53b201-54c6-6208-a666-33e15d7eb5a0",
  "meta": {
    "profile": [
      "http://hl7.org/fhir/R4/observation.html"
    ],
    "versionId": "1",
    "lastUpdated": "2025-08-28T05:15:43.576383"
  },
  "status": "final",
  "subject": {
    "reference": "Patient/9a6530b6-31bc-ab7d-04b1-8a634cfaa18c"
  },
  "code": {
    "coding": [
      {
        "system": "http://tmu.edu.tw/fhir/alzheimers/observation",
        "code": "bb9afaaebf1de877",
        "display": "編號"
      }
    ],
    "text": "編號"
  },
  "valueQuantity": {
    "value": 54.0,
    "unit": "",
    "system": "http://unitsofmeasure.org",
    "code": ""
  }
}