{
  "resourceType": "Observation",
  "id": "115c6269-aa56-a4c5-256d-b874f8aba6d6",
  "meta": {
    "profile": [
      "http://hl7.org/fhir/R4/observation.html"
    ],
    "versionId": "1",
    "lastUpdated": "2025-08-28T05:15:42.197422"
  },
  "status": "final",
  "subject": {
    "reference": "Patient/73bad4b0-ce77-6016-db51-b7c945588070"
  },
  "code": {
    "coding": [
      {
        "system": "http://tmu.edu.tw/fhir/alzheimers/observation",
        "code": "f1ce456113e10ba0",
        "display": "西元"
      }
    ],
    "text": "西元"
  },
  "valueString": "1938/06/10"
}