{
  "resourceType": "Observation",
  "id": "22b7ec12-e687-15f6-9c7d-bd0f145a5405",
  "meta": {
    "profile": [
      "http://hl7.org/fhir/R4/observation.html"
    ],
    "versionId": "1",
    "lastUpdated": "2025-08-28T05:15:41.025088"
  },
  "status": "final",
  "subject": {
    "reference": "Patient/e4c8a542-a326-e3ec-6b76-516a88571e72"
  },
  "code": {
    "coding": [
      {
        "system": "http://tmu.edu.tw/fhir/alzheimers/observation",
        "code": "e000d4c30b58520f",
        "display": "確診日期"
      }
    ],
    "text": "確診日期"
  },
  "valueString": "0112/02/21"
}