{
  "resourceType": "Observation",
  "id": "39ee2562-0042-26b9-15be-0d4c03da448a",
  "meta": {
    "profile": [
      "http://hl7.org/fhir/R4/observation.html"
    ],
    "versionId": "1",
    "lastUpdated": "2025-08-28T05:15:43.589170"
  },
  "status": "final",
  "subject": {
    "reference": "Patient/d019cc6c-f479-1be5-f320-2998eecd628f"
  },
  "code": {
    "coding": [
      {
        "system": "http://tmu.edu.tw/fhir/alzheimers/observation",
        "code": "2739dd705a100f27",
        "display": "收案日期"
      }
    ],
    "text": "收案日期"
  },
  "valueString": "0113/04/02"
}