{
  "resourceType": "Observation",
  "id": "401febbc-5d9a-d400-ebf5-3ea523bffed3",
  "meta": {
    "profile": [
      "http://hl7.org/fhir/R4/observation.html"
    ],
    "versionId": "1",
    "lastUpdated": "2025-08-28T05:15:43.636340"
  },
  "status": "final",
  "subject": {
    "reference": "Patient/c3735a25-c1dc-72a8-43c6-3f6872cd82e0"
  },
  "code": {
    "coding": [
      {
        "system": "http://tmu.edu.tw/fhir/alzheimers/observation",
        "code": "82f5585da95c6870",
        "display": "0.5程度分級"
      }
    ],
    "text": "0.5程度分級"
  },
  "valueString": "VMD"
}