{
  "resourceType": "Observation",
  "id": "497ea312-b570-7cf2-3fa8-0085105dc4db",
  "meta": {
    "profile": [
      "http://hl7.org/fhir/R4/observation.html"
    ],
    "versionId": "1",
    "lastUpdated": "2025-08-28T05:15:41.046959"
  },
  "status": "final",
  "subject": {
    "reference": "Patient/6ac75cb6-3bb0-2ac2-7149-fcf5f3c4409a"
  },
  "code": {
    "coding": [
      {
        "system": "http://tmu.edu.tw/fhir/alzheimers/observation",
        "code": "bb9afaaebf1de877",
        "display": "編號"
      }
    ],
    "text": "編號"
  },
  "valueQuantity": {
    "value": 277.0,
    "unit": "",
    "system": "http://unitsofmeasure.org",
    "code": ""
  }
}