{
  "resourceType": "Observation",
  "id": "53ec2b47-bd3b-31af-378e-5a7c74a0d869",
  "meta": {
    "profile": [
      "http://hl7.org/fhir/R4/observation.html"
    ],
    "versionId": "1",
    "lastUpdated": "2025-08-28T05:14:38.822602"
  },
  "status": "final",
  "subject": {
    "reference": "Patient/32497b62-b5bd-381a-4ca4-776c7dd0d608"
  },
  "code": {
    "coding": [
      {
        "system": "http://tmu.edu.tw/fhir/alzheimers/observation",
        "code": "2739dd705a100f27",
        "display": "收案日期"
      }
    ],
    "text": "收案日期"
  },
  "valueString": "2021-07-03"
}