{
  "resourceType": "Observation",
  "id": "6294e588-2c42-3023-cf60-2657111848fa",
  "meta": {
    "profile": [
      "http://hl7.org/fhir/R4/observation.html"
    ],
    "versionId": "1",
    "lastUpdated": "2025-08-28T05:15:42.212583"
  },
  "status": "final",
  "subject": {
    "reference": "Patient/5eae2d65-b12f-4d11-f7c3-eac90fa95a6b"
  },
  "code": {
    "coding": [
      {
        "system": "http://tmu.edu.tw/fhir/alzheimers/observation",
        "code": "20ca7d27c0cd376f",
        "display": "Unnamed: 2"
      }
    ],
    "text": "Unnamed: 2"
  },
  "valueString": "男"
}