{
  "resourceType": "Observation",
  "id": "6e2159de-a203-9e4f-8976-1bc23299b237",
  "meta": {
    "profile": [
      "http://hl7.org/fhir/R4/observation.html"
    ],
    "versionId": "1",
    "lastUpdated": "2025-08-28T05:15:43.593566"
  },
  "status": "final",
  "subject": {
    "reference": "Patient/3fa6716e-c9ff-a02e-2c88-75d0638e7884"
  },
  "code": {
    "coding": [
      {
        "system": "http://tmu.edu.tw/fhir/alzheimers/observation",
        "code": "bb9afaaebf1de877",
        "display": "編號"
      }
    ],
    "text": "編號"
  },
  "valueQuantity": {
    "value": 239.0,
    "unit": "",
    "system": "http://unitsofmeasure.org",
    "code": ""
  }
}