{
  "resourceType": "Observation",
  "id": "85e21fb9-0a62-0aed-e336-40ded2fed2e6",
  "meta": {
    "profile": [
      "http://hl7.org/fhir/R4/observation.html"
    ],
    "versionId": "1",
    "lastUpdated": "2025-08-28T05:15:42.218925"
  },
  "status": "final",
  "subject": {
    "reference": "Patient/9a9bb367-70de-7a80-ac36-8e885f7e009c"
  },
  "code": {
    "coding": [
      {
        "system": "http://tmu.edu.tw/fhir/alzheimers/observation",
        "code": "f1ce456113e10ba0",
        "display": "西元"
      }
    ],
    "text": "西元"
  },
  "valueString": "1939/11/06"
}