{
  "resourceType": "Observation",
  "id": "94bae7be-e433-665b-b433-ca6b6ae39765",
  "meta": {
    "profile": [
      "http://hl7.org/fhir/R4/observation.html"
    ],
    "versionId": "1",
    "lastUpdated": "2025-08-28T05:15:43.602654"
  },
  "status": "final",
  "subject": {
    "reference": "Patient/485865c4-ecea-352a-abc9-06544734814b"
  },
  "code": {
    "coding": [
      {
        "system": "http://tmu.edu.tw/fhir/alzheimers/observation",
        "code": "82f5585da95c6870",
        "display": "0.5程度分級"
      }
    ],
    "text": "0.5程度分級"
  },
  "valueString": "VMD"
}