{
  "resourceType": "Observation",
  "id": "a692a345-82f1-1b2b-5ab4-b286716ff2af",
  "meta": {
    "profile": [
      "http://hl7.org/fhir/R4/observation.html"
    ],
    "versionId": "1",
    "lastUpdated": "2025-08-28T05:15:42.175009"
  },
  "status": "final",
  "subject": {
    "reference": "Patient/62778d28-3a28-a116-de3c-2dbfe7a2094d"
  },
  "code": {
    "coding": [
      {
        "system": "http://tmu.edu.tw/fhir/alzheimers/observation",
        "code": "2739dd705a100f27",
        "display": "收案日期"
      }
    ],
    "text": "收案日期"
  },
  "valueString": "2018-06-01 0:00:00"
}