{
  "resourceType": "Observation",
  "id": "ad50173b-10a8-a4ef-23e3-f295bf8e4a01",
  "meta": {
    "profile": [
      "http://hl7.org/fhir/R4/observation.html"
    ],
    "versionId": "1",
    "lastUpdated": "2025-08-28T05:15:43.598148"
  },
  "status": "final",
  "subject": {
    "reference": "Patient/c045478a-f106-0272-473c-a171c85e923f"
  },
  "code": {
    "coding": [
      {
        "system": "http://tmu.edu.tw/fhir/alzheimers/observation",
        "code": "2739dd705a100f27",
        "display": "收案日期"
      }
    ],
    "text": "收案日期"
  },
  "valueString": "0113/05/07"
}