{
  "resourceType": "Observation",
  "id": "bf56e089-cb1b-88c1-0223-c8f896391056",
  "meta": {
    "profile": [
      "http://hl7.org/fhir/R4/observation.html"
    ],
    "versionId": "1",
    "lastUpdated": "2025-08-28T05:15:41.076502"
  },
  "status": "final",
  "subject": {
    "reference": "Patient/c6d0442e-e341-8019-6ed9-f33fee5530b2"
  },
  "code": {
    "coding": [
      {
        "system": "http://tmu.edu.tw/fhir/alzheimers/observation",
        "code": "bb9afaaebf1de877",
        "display": "編號"
      }
    ],
    "text": "編號"
  },
  "valueQuantity": {
    "value": 572.0,
    "unit": "",
    "system": "http://unitsofmeasure.org",
    "code": ""
  }
}