{
  "resourceType": "Observation",
  "id": "cdae42c0-bf2b-f894-d675-228b17747e15",
  "meta": {
    "profile": [
      "http://hl7.org/fhir/R4/observation.html"
    ],
    "versionId": "1",
    "lastUpdated": "2025-08-28T05:14:39.547374"
  },
  "status": "final",
  "subject": {
    "reference": "Patient/5fac92b8-66ca-064b-6d7d-567ef3d78da3"
  },
  "code": {
    "coding": [
      {
        "system": "http://tmu.edu.tw/fhir/alzheimers/observation",
        "code": "2739dd705a100f27",
        "display": "收案日期"
      }
    ],
    "text": "收案日期"
  },
  "valueString": "2019-05-20 0:00:00"
}