{
  "resourceType": "Observation",
  "id": "d30f69fd-432f-6910-275f-57ea8fa669b5",
  "meta": {
    "profile": [
      "http://hl7.org/fhir/R4/observation.html"
    ],
    "versionId": "1",
    "lastUpdated": "2025-08-28T05:15:43.620162"
  },
  "status": "final",
  "subject": {
    "reference": "Patient/cb040fc3-7705-5475-ca8e-4cefa7e2ecf3"
  },
  "code": {
    "coding": [
      {
        "system": "http://tmu.edu.tw/fhir/alzheimers/observation",
        "code": "2739dd705a100f27",
        "display": "收案日期"
      }
    ],
    "text": "收案日期"
  },
  "valueString": "0113/07/30"
}