{
  "resourceType": "Observation",
  "id": "d5929085-ecdb-e82f-5a43-857a945bc9f0",
  "meta": {
    "profile": [
      "http://hl7.org/fhir/R4/observation.html"
    ],
    "versionId": "1",
    "lastUpdated": "2025-08-28T05:15:41.021827"
  },
  "status": "final",
  "subject": {
    "reference": "Patient/88644fa9-b953-d65d-a56d-da2de068ced4"
  },
  "code": {
    "coding": [
      {
        "system": "http://tmu.edu.tw/fhir/alzheimers/observation",
        "code": "bb9afaaebf1de877",
        "display": "編號"
      }
    ],
    "text": "編號"
  },
  "valueQuantity": {
    "value": 74.0,
    "unit": "",
    "system": "http://unitsofmeasure.org",
    "code": ""
  }
}