{
  "resourceType": "Observation",
  "id": "dea6ff75-059e-b480-ead5-25cf59213d80",
  "meta": {
    "profile": [
      "http://hl7.org/fhir/R4/observation.html"
    ],
    "versionId": "1",
    "lastUpdated": "2025-08-28T05:15:06.831119"
  },
  "status": "final",
  "subject": {
    "reference": "Patient/df233dae-fffe-2fd1-41bc-df0749af48d0"
  },
  "code": {
    "coding": [
      {
        "system": "http://tmu.edu.tw/fhir/alzheimers/observation",
        "code": "cb2a19d31dd6e359",
        "display": "確診/看診醫師"
      }
    ],
    "text": "確診/看診醫師"
  },
  "valueString": "胡朝榮"
}