{
  "resourceType": "Observation",
  "id": "e2781520-bf56-bad8-16bd-9610b9db449a",
  "meta": {
    "profile": [
      "http://hl7.org/fhir/R4/observation.html"
    ],
    "versionId": "1",
    "lastUpdated": "2025-08-28T05:15:42.228519"
  },
  "status": "final",
  "subject": {
    "reference": "Patient/0f4c1905-dcd0-0be0-bf4f-ac07c581f317"
  },
  "code": {
    "coding": [
      {
        "system": "http://tmu.edu.tw/fhir/alzheimers/observation",
        "code": "e37502001c891ca8",
        "display": "NCV檢查"
      }
    ],
    "text": "NCV檢查"
  },
  "valueString": "N"
}